junipercs/__init__.py
junipercs/__main__.py
junipercs/juniper_source.py
junipercs/parsetab.py
junipercs/modules/__init__.py
junipercs/modules/create.py
junipercs/modules/goto.py
junipercs/modules/list.py
junipercs/modules/options.py
junipercs/ply/__init__.py
junipercs/ply/cpp.py
junipercs/ply/ctokens.py
junipercs/ply/lex.py
junipercs/ply/yacc.py
junipercs/ply/ygen.py
junipercs/resources/__init__.py
junipercs/resources/commands_list.py
junipercs/system_parser/__init__.py
junipercs/system_parser/tokens.py
junipercs/system_parser/tokens_definition.py
junipertest-0.0.22.dist-info/LICENSE
junipertest-0.0.22.dist-info/METADATA
junipertest-0.0.22.dist-info/WHEEL
junipertest-0.0.22.dist-info/top_level.txt
junipertest-0.0.22.dist-info/RECORD
